shapeout/ShapeOut.py
shapeout/__init__.py
shapeout/__main__.py
shapeout/_version.py
shapeout/_version_save.py
shapeout/analysis.py
shapeout/lin_mix_mod.py
shapeout/meta_tool.py
shapeout/settings.py
shapeout/cfg/default.cfg
shapeout/data/isoel-analytical-area_um-deform_legacy.txt
shapeout/external/__init__.py
shapeout/external/backport_chaco_viridis.py
shapeout/gui/__init__.py
shapeout/gui/autosave.py
shapeout/gui/batch.py
shapeout/gui/confparms.py
shapeout/gui/controls.py
shapeout/gui/controls_analyze.py
shapeout/gui/controls_calculate.py
shapeout/gui/controls_contourplot.py
shapeout/gui/controls_filter.py
shapeout/gui/controls_info.py
shapeout/gui/controls_plotting.py
shapeout/gui/controls_scatterplot.py
shapeout/gui/controls_statistics.py
shapeout/gui/controls_subpanel.py
shapeout/gui/explorer.py
shapeout/gui/export.py
shapeout/gui/frontend.py
shapeout/gui/gaugeframe.py
shapeout/gui/help.py
shapeout/gui/icon.py
shapeout/gui/misc.py
shapeout/gui/plot_common.py
shapeout/gui/plot_contour.py
shapeout/gui/plot_export.py
shapeout/gui/plot_legend.py
shapeout/gui/plot_main.py
shapeout/gui/plot_scatter.py
shapeout/gui/polygonselect.py
shapeout/gui/session_ui.py
shapeout/gui/update.py
shapeout/gui/video.py
shapeout/img/LICENSE
shapeout/img/shapeout_logotype_h36.png
shapeout/img/shapeout_logotype_h50.png
shapeout/img/transparent_h50.png
shapeout/img/zm_icon.png
shapeout/img/zm_logo.png
shapeout/img/zm_logo_h36.png
shapeout/img/zm_logo_h50.png
shapeout/img/zm_logo_small.png
shapeout/img/zm_logo_small_bgwhite.png
shapeout/session/__init__.py
shapeout/session/conversion.py
shapeout/session/index.py
shapeout/session/rw.py
shapeout/util/__init__.py
shapeout/util/cran.py
shapeout/util/spath.py
shapeout-1.0.10.dist-info/LICENSE
shapeout-1.0.10.dist-info/METADATA
shapeout-1.0.10.dist-info/WHEEL
shapeout-1.0.10.dist-info/top_level.txt
shapeout-1.0.10.dist-info/RECORD
