Metadata-Version: 2.1
Name: shapeout
Version: 1.0.10
Summary: User interface for real-time deformability cytometry (RT-DC)
Home-page: https://github.com/ZELLMECHANIK-DRESDEN/ShapeOut
Author: Paul Müller
Author-email: dev@craban.de
License: GPL v2
Keywords: RT-DC,deformability,cytometry,zellmechanik
Platform: ALL
Classifier: Operating System :: OS Independent
Classifier: Programming Language :: Python :: 2.7
Classifier: Intended Audience :: Science/Research
Requires-Dist: appdirs
Requires-Dist: dclab[all] (>=0.25.0)
Requires-Dist: fcswrite (>=0.5.0)
Requires-Dist: h5py (>=2.8.0)
Requires-Dist: imageio (<2.5.0,>=2.3.0)
Requires-Dist: nptdms (>=0.23.0)
Requires-Dist: numpy (>=1.9.0)
Requires-Dist: pathlib
Requires-Dist: pyper
Requires-Dist: scipy (>=0.13.0)
Provides-Extra: gui
Requires-Dist: chaco ; extra == 'gui'
Requires-Dist: simplejson ; extra == 'gui'
Requires-Dist: wxPython (<4.0.0,>=3.0.0) ; extra == 'gui'
Requires-Dist: kiwisolver ; extra == 'gui'
Requires-Dist: reportlab ; extra == 'gui'
Provides-Extra: test
Requires-Dist: pytest (<5.0) ; extra == 'test'
Requires-Dist: urllib3 ; extra == 'test'
Requires-Dist: configparser (==3.5) ; extra == 'test'
Requires-Dist: zipp (==0.5) ; extra == 'test'
Requires-Dist: pyparsing (==2.4.6) ; extra == 'test'
